adminStat/__init__.py
adminStat/asgi.py
adminStat/settings.py
adminStat/urls.py
adminStat/wsgi.py
apistat/__init__.py
apistat/admin.py
apistat/apps.py
apistat/models.py
apistat/serializers.py
apistat/tests.py
apistat/urls.py
apistat/views.py
apistat/migrations/0001_initial.py
apistat/migrations/0002_apistatspr_db_alias.py
apistat/migrations/__init__.py
django_apistat-0.2.2.dist-info/LICENSE.rst
django_apistat-0.2.2.dist-info/METADATA
django_apistat-0.2.2.dist-info/WHEEL
django_apistat-0.2.2.dist-info/top_level.txt
django_apistat-0.2.2.dist-info/RECORD
