Metadata-Version: 2.1
Name: django-apistat
Version: 0.2.2
Summary: Result JSON from sql report in db
Home-page: UNKNOWN
Author: UNKNOWN
Author-email: UNKNOWN
License: BSD 3-Clause License
Keywords: json,sql,django,api,statistic
Platform: UNKNOWN
Classifier: Framework :: Django
Classifier: License :: OSI Approved :: BSD License
Classifier: Programming Language :: Python :: 3
Classifier: Programming Language :: Python :: 3.5
Requires-Dist: requests
Requires-Dist: importlib ; python_version == "2.6"
